hex_dynamic-0.1.3.dist-info/METADATA
hex_dynamic-0.1.3.dist-info/WHEEL
hex_dynamic/__init__.py
hex_dynamic/hex_dynamic.abi3.so
hex_dynamic-0.1.3.dist-info/RECORD
