Metadata-Version: 2.4
Name: hex_dynamic
Version: 0.1.3
Classifier: Development Status :: 3 - Alpha
Classifier: Programming Language :: Python
Classifier: Programming Language :: Python :: 3
Classifier: Programming Language :: Python :: 3 :: Only
Classifier: Programming Language :: Python :: 3.8
Classifier: Programming Language :: Python :: 3.9
Classifier: Programming Language :: Python :: 3.10
Classifier: Programming Language :: Python :: 3.11
Classifier: Programming Language :: Python :: 3.12
Classifier: Programming Language :: Rust
Classifier: Intended Audience :: Developers
Summary: A Python extension module written in Rust using PyO3
Keywords: python,rust,pyo3,extension-module
Author-email: Cursor & LLM <cursor@llm.com>
Requires-Python: >=3.8
